{"specVersion":"1.4","version":1,"metadata":{"timestamp":"2024-10-13T00:28:35Z"},"components":[{"type":"application","name":"ca-bundle","licenses":[{"license":{"name":"GPL-2.0-or-later"}},{"license":{"name":"MPL-2.0"}}],"version":"20240203"},{"type":"application","licenses":[{"license":{"name":"GPL-2.0-or-later"}},{"license":{"name":"MPL-2.0"}}],"version":"20240203","name":"ca-certificates"},{"licenses":[{"license":{"name":"GPL-2.0"}}],"version":"2024.10.01~714e4199","name":"iwinfo","type":"application"},{"name":"jshn","licenses":[{"license":{"name":"ISC"}}],"version":"2024.03.29~eb9bcb64","type":"application"},{"name":"libblobmsg-json20240329","licenses":[{"license":{"name":"ISC"}}],"version":"2024.03.29~eb9bcb64","type":"library"},{"type":"application","version":"2024.10.01~714e4199","licenses":[{"license":{"name":"GPL-2.0"}}],"name":"libiwinfo-data"},{"version":"2024.10.01~714e4199","licenses":[{"license":{"name":"GPL-2.0"}}],"name":"libiwinfo-lua","type":"application"},{"type":"library","name":"libiwinfo20230701","licenses":[{"license":{"name":"GPL-2.0"}}],"version":"2024.10.01~714e4199"},{"name":"libjson-c5","version":"0.18","cpe":"cpe:/a:json-c:json-c:0.18","licenses":[{"license":{"name":"MIT"}}],"type":"library"},{"type":"application","name":"libjson-script20240329","licenses":[{"license":{"name":"ISC"}}],"version":"2024.03.29~eb9bcb64"},{"type":"library","name":"liblua5.1.5","licenses":[{"license":{"name":"MIT"}}],"cpe":"cpe:/a:lua:lua:5.1.5","version":"5.1.5"},{"name":"libmbedtls21","cpe":"cpe:/a:arm:mbed_tls:3.6.1","licenses":[{"license":{"name":"GPL-2.0-or-later"}}],"version":"3.6.1","type":"library"},{"name":"libnl-tiny1","version":"2023.12.05~965c4bf4","licenses":[{"license":{"name":"LGPL-2.1"}}],"type":"library"},{"type":"library","name":"libopenssl-afalg","licenses":[{"license":{"name":"Apache-2.0"}}],"cpe":"cpe:/a:openssl:openssl:3.0.15","version":"3.0.15"},{"cpe":"cpe:/a:openssl:openssl:3.0.15","licenses":[{"license":{"name":"Apache-2.0"}}],"version":"3.0.15","name":"libopenssl-conf","type":"library"},{"name":"libopenssl-devcrypto","cpe":"cpe:/a:openssl:openssl:3.0.15","version":"3.0.15","licenses":[{"license":{"name":"Apache-2.0"}}],"type":"library"},{"name":"libopenssl-legacy","cpe":"cpe:/a:openssl:openssl:3.0.15","licenses":[{"license":{"name":"Apache-2.0"}}],"version":"3.0.15","type":"library"},{"type":"library","licenses":[{"license":{"name":"Apache-2.0"}}],"cpe":"cpe:/a:openssl:openssl:3.0.15","version":"3.0.15","name":"libopenssl-padlock"},{"name":"libopenssl3","licenses":[{"license":{"name":"Apache-2.0"}}],"cpe":"cpe:/a:openssl:openssl:3.0.15","version":"3.0.15","type":"library"},{"licenses":[{"license":{"name":"ISC"}}],"version":"2024.03.29~eb9bcb64","name":"libubox-lua","type":"library"},{"type":"library","name":"libubox20240329","version":"2024.03.29~eb9bcb64","licenses":[{"license":{"name":"ISC"}}]},{"type":"library","name":"libubus-lua","version":"2023.11.28~f84eb599","licenses":[{"license":{"name":"LGPL-2.1"}}]},{"version":"2023.11.28~f84eb599","licenses":[{"license":{"name":"LGPL-2.1"}}],"name":"libubus20231128","type":"library"},{"type":"library","licenses":[{"license":{"name":"LGPL-2.1"}}],"version":"2023.08.10~5781664d","name":"libuci-lua"},{"type":"library","name":"libuci20130104","licenses":[{"license":{"name":"LGPL-2.1"}}],"version":"2023.08.10~5781664d"},{"name":"libucode20230711","licenses":[{"license":{"name":"ISC"}}],"version":"2024.07.22~b610860d","type":"library"},{"name":"lua","version":"5.1.5","cpe":"cpe:/a:lua:lua:5.1.5","licenses":[{"license":{"name":"MIT"}}],"type":"application"},{"name":"lua-examples","version":"5.1.5","cpe":"cpe:/a:lua:lua:5.1.5","licenses":[{"license":{"name":"MIT"}}],"type":"application"},{"type":"application","name":"luac","cpe":"cpe:/a:lua:lua:5.1.5","version":"5.1.5","licenses":[{"license":{"name":"MIT"}}]},{"type":"application","version":"1.6.6-1","name":"luci-app-mosdns"},{"type":"application","version":"0.46.033-rbeta","name":"luci-app-openclash"},{"name":"luci-i18n-mosdns-zh-cn","version":"24.279.63190~370fcaf","type":"application"},{"type":"application","cpe":"cpe:/a:arm:mbed_tls:3.6.1","version":"3.6.1","licenses":[{"license":{"name":"GPL-2.0-or-later"}}],"name":"mbedtls-util"},{"type":"application","licenses":[{"license":{"name":"MIT"}}],"version":"20211210-master","name":"neofetch"},{"name":"openssl-util","licenses":[{"license":{"name":"Apache-2.0"}}],"cpe":"cpe:/a:openssl:openssl:3.0.15","version":"3.0.15","type":"application"},{"licenses":[{"license":{"name":"ISC"}}],"version":"2024.09.17~9f4b86e7","name":"rpcd","type":"application"},{"licenses":[{"license":{"name":"ISC"}}],"version":"2024.09.17~9f4b86e7","name":"rpcd-mod-file","type":"application"},{"name":"rpcd-mod-iwinfo","version":"2024.09.17~9f4b86e7","licenses":[{"license":{"name":"ISC"}}],"type":"application"},{"licenses":[{"license":{"name":"ISC"}}],"version":"2024.09.17~9f4b86e7","name":"rpcd-mod-rpcsys","type":"application"},{"name":"rpcd-mod-ucode","version":"2024.09.17~9f4b86e7","licenses":[{"license":{"name":"ISC"}}],"type":"application"},{"type":"application","licenses":[{"license":{"name":"BSD-3-Clause"}}],"version":"1.58.2","name":"tailscale"},{"name":"traefik","version":"2.10.7","licenses":[{"license":{"name":"MIT"}}],"type":"application"},{"licenses":[{"license":{"name":"LGPL-2.1"}}],"version":"2023.11.28~f84eb599","name":"ubus","type":"application"},{"type":"application","licenses":[{"license":{"name":"LGPL-2.1"}}],"version":"2023.11.28~f84eb599","name":"ubusd"},{"type":"application","licenses":[{"license":{"name":"LGPL-2.1"}}],"version":"2023.08.10~5781664d","name":"uci"},{"licenses":[{"license":{"name":"ISC"}}],"version":"2024.07.22~b610860d","name":"ucode","type":"application"},{"type":"application","name":"ucode-mod-debug","licenses":[{"license":{"name":"ISC"}}],"version":"2024.07.22~b610860d"},{"type":"application","name":"ucode-mod-fs","version":"2024.07.22~b610860d","licenses":[{"license":{"name":"ISC"}}]},{"type":"application","name":"ucode-mod-log","version":"2024.07.22~b610860d","licenses":[{"license":{"name":"ISC"}}]},{"version":"2024.07.22~b610860d","licenses":[{"license":{"name":"ISC"}}],"name":"ucode-mod-math","type":"application"},{"version":"2024.07.22~b610860d","licenses":[{"license":{"name":"ISC"}}],"name":"ucode-mod-nl80211","type":"application"},{"name":"ucode-mod-resolv","version":"2024.07.22~b610860d","licenses":[{"license":{"name":"ISC"}}],"type":"application"},{"type":"application","licenses":[{"license":{"name":"ISC"}}],"version":"2024.07.22~b610860d","name":"ucode-mod-rtnl"},{"name":"ucode-mod-socket","version":"2024.07.22~b610860d","licenses":[{"license":{"name":"ISC"}}],"type":"application"},{"licenses":[{"license":{"name":"ISC"}}],"version":"2024.07.22~b610860d","name":"ucode-mod-struct","type":"application"},{"type":"application","name":"ucode-mod-ubus","licenses":[{"license":{"name":"ISC"}}],"version":"2024.07.22~b610860d"},{"licenses":[{"license":{"name":"ISC"}}],"version":"2024.07.22~b610860d","name":"ucode-mod-uci","type":"application"},{"licenses":[{"license":{"name":"ISC"}}],"version":"2024.07.22~b610860d","name":"ucode-mod-uloop","type":"application"},{"version":"2022.12.15~47b8ee51","licenses":[{"license":{"name":"GPL-3.0"}}],"name":"v2dat","type":"application"},{"name":"v2ray-geoip","version":"2024-10-13","licenses":[{"license":{"name":"CC-BY-SA-4.0"}}],"type":"application"},{"type":"application","version":"2024-10-13","licenses":[{"license":{"name":"GPL-3.0"}}],"name":"v2ray-geosite"},{"type":"application","name":"vector","licenses":[{"license":{"name":"MIT"}}],"version":"0.41.1"},{"name":"zlib","cpe":"cpe:/a:gnu:zlib:1.3.1","version":"1.3.1","licenses":[{"license":{"name":"Zlib"}}],"type":"library"},{"type":"application","name":"zlib-dev","cpe":"cpe:/a:gnu:zlib:1.3.1","version":"1.3.1","licenses":[{"license":{"name":"Zlib"}}]}],"bomFormat":"CycloneDX","serialNumber":"urn:uuid:1fb68244-2668-4bf8-a500-f20512463615"}